[{"Nombre Comercial":"ADMINISTRACIONES TURISTICAS REFORMA","Cantidad":4,"Producto":"Tortilla de Ma\u00edz 800gr.  (Natural, Chica (12), Normal)","Direcci\u00f3n":null,"Horario de Recepci\u00f3n":null,"Acuse de Recepci\u00f3n":null,"Instrucciones":null},{"Nombre Comercial":"","Cantidad":44,"Producto":"Tortilla de Ma\u00edz 800gr.  (Natural, Est\u00e1ndar(15cm), Normal)","Direcci\u00f3n":null,"Horario de Recepci\u00f3n":null,"Acuse de Recepci\u00f3n":null,"Instrucciones":null},{"Nombre Comercial":"","Cantidad":1,"Producto":"MASA (Azul)","Direcci\u00f3n":null,"Horario de Recepci\u00f3n":null,"Acuse de Recepci\u00f3n":null,"Instrucciones":null},{"Nombre Comercial":"","Cantidad":1,"Producto":"Totopos (Nopal)","Direcci\u00f3n":null,"Horario de Recepci\u00f3n":null,"Acuse de Recepci\u00f3n":null,"Instrucciones":null},{"Nombre Comercial":"","Cantidad":1,"Producto":"Totopos (Ma\u00edz Azul)","Direcci\u00f3n":null,"Horario de Recepci\u00f3n":null,"Acuse de Recepci\u00f3n":null,"Instrucciones":null},{"Nombre Comercial":"","Cantidad":1,"Producto":"Totopos (Espinaca)","Direcci\u00f3n":null,"Horario de Recepci\u00f3n":null,"Acuse de Recepci\u00f3n":null,"Instrucciones":null},{"Nombre Comercial":"","Cantidad":1,"Producto":"Totopos (Betabel)","Direcci\u00f3n":null,"Horario de Recepci\u00f3n":null,"Acuse de Recepci\u00f3n":null,"Instrucciones":null},{"Nombre Comercial":"","Cantidad":1,"Producto":"Totopos (Achiote)","Direcci\u00f3n":null,"Horario de Recepci\u00f3n":null,"Acuse de Recepci\u00f3n":null,"Instrucciones":null},{"Nombre Comercial":"MARISQUERIA MAVIRI","Cantidad":2,"Producto":"Tortilla para Fre\u00edr 800 gr.  (Est\u00e1ndar (16 cm), Normal)","Direcci\u00f3n":null,"Horario de Recepci\u00f3n":null,"Acuse de Recepci\u00f3n":null,"Instrucciones":null},{"Nombre Comercial":"","Cantidad":48,"Producto":"Tortilla de Ma\u00edz 800gr.  (Ma\u00edz Azul, Est\u00e1ndar(15cm), Normal)","Direcci\u00f3n":null,"Horario de Recepci\u00f3n":null,"Acuse de Recepci\u00f3n":null,"Instrucciones":null},{"Nombre Comercial":"","Cantidad":12,"Producto":"Tortilla de Ma\u00edz 800gr.  (Natural, Est\u00e1ndar(15cm), Normal)","Direcci\u00f3n":null,"Horario de Recepci\u00f3n":null,"Acuse de Recepci\u00f3n":null,"Instrucciones":null},{"Nombre Comercial":"PIMIENTO NEGRO","Cantidad":20,"Producto":"Tortilla de Ma\u00edz 800gr.  (Ma\u00edz Azul, Grande (14 cm), Normal)","Direcci\u00f3n":null,"Horario de Recepci\u00f3n":null,"Acuse de Recepci\u00f3n":null,"Instrucciones":null},{"Nombre Comercial":"","Cantidad":10,"Producto":"Tostadas (Chipotle, 25 Piezas)","Direcci\u00f3n":null,"Horario de Recepci\u00f3n":null,"Acuse de Recepci\u00f3n":null,"Instrucciones":null},{"Nombre Comercial":"","Cantidad":8,"Producto":"Tostadas (Ma\u00edz Azul, 25 Piezas)","Direcci\u00f3n":null,"Horario de Recepci\u00f3n":null,"Acuse de Recepci\u00f3n":null,"Instrucciones":null},{"Nombre Comercial":"","Cantidad":10,"Producto":"Tortilla de Ma\u00edz 800gr.  (Natural, Est\u00e1ndar(15cm), Normal)","Direcci\u00f3n":null,"Horario de Recepci\u00f3n":null,"Acuse de Recepci\u00f3n":null,"Instrucciones":null},{"Nombre Comercial":"","Cantidad":30,"Producto":"Huaraches (Natural, Frijol, Est\u00e1ndar (28 CM))","Direcci\u00f3n":null,"Horario de Recepci\u00f3n":null,"Acuse de Recepci\u00f3n":null,"Instrucciones":null},{"Nombre Comercial":"PUERCO PI\u00d1A","Cantidad":5,"Producto":"MASA (Azul)","Direcci\u00f3n":null,"Horario de Recepci\u00f3n":null,"Acuse de Recepci\u00f3n":null,"Instrucciones":null}]